iopaint/__init__.py
iopaint/__main__.py
iopaint/api.py
iopaint/batch_processing.py
iopaint/benchmark.py
iopaint/cli.py
iopaint/const.py
iopaint/download.py
iopaint/helper.py
iopaint/installer.py
iopaint/model_manager.py
iopaint/runtime.py
iopaint/schema.py
iopaint/web_config.py
iopaint/file_manager/__init__.py
iopaint/file_manager/file_manager.py
iopaint/file_manager/storage_backends.py
iopaint/file_manager/utils.py
iopaint/model/__init__.py
iopaint/model/base.py
iopaint/model/controlnet.py
iopaint/model/ddim_sampler.py
iopaint/model/fcf.py
iopaint/model/instruct_pix2pix.py
iopaint/model/kandinsky.py
iopaint/model/lama.py
iopaint/model/ldm.py
iopaint/model/manga.py
iopaint/model/mat.py
iopaint/model/mi_gan.py
iopaint/model/opencv2.py
iopaint/model/paint_by_example.py
iopaint/model/plms_sampler.py
iopaint/model/sd.py
iopaint/model/sdxl.py
iopaint/model/utils.py
iopaint/model/zits.py
iopaint/model/anytext/__init__.py
iopaint/model/anytext/anytext_model.py
iopaint/model/anytext/anytext_pipeline.py
iopaint/model/anytext/anytext_sd15.yaml
iopaint/model/anytext/main.py
iopaint/model/anytext/utils.py
iopaint/model/anytext/cldm/__init__.py
iopaint/model/anytext/cldm/cldm.py
iopaint/model/anytext/cldm/ddim_hacked.py
iopaint/model/anytext/cldm/embedding_manager.py
iopaint/model/anytext/cldm/hack.py
iopaint/model/anytext/cldm/model.py
iopaint/model/anytext/cldm/recognizer.py
iopaint/model/anytext/ldm/__init__.py
iopaint/model/anytext/ldm/util.py
iopaint/model/anytext/ldm/models/__init__.py
iopaint/model/anytext/ldm/models/autoencoder.py
iopaint/model/anytext/ldm/models/diffusion/__init__.py
iopaint/model/anytext/ldm/models/diffusion/ddim.py
iopaint/model/anytext/ldm/models/diffusion/ddpm.py
iopaint/model/anytext/ldm/models/diffusion/plms.py
iopaint/model/anytext/ldm/models/diffusion/sampling_util.py
iopaint/model/anytext/ldm/models/diffusion/dpm_solver/__init__.py
iopaint/model/anytext/ldm/models/diffusion/dpm_solver/dpm_solver.py
IOPaint-1.6.0.dist-info/LICENSE
IOPaint-1.6.0.dist-info/METADATA
IOPaint-1.6.0.dist-info/WHEEL
IOPaint-1.6.0.dist-info/entry_points.txt
IOPaint-1.6.0.dist-info/top_level.txt
IOPaint-1.6.0.dist-info/RECORD
