Metadata-Version: 2.1
Name: IOPaint
Version: 1.6.0
Summary: Image inpainting, outpainting tool powered by SOTA AI Model
Home-page: https://github.com/Sanster/IOPaint
Author: PanicByte
Author-email: cwq1913@gmail.com
Classifier: License :: OSI Approved :: Apache Software License
Classifier: Operating System :: OS Independent
Classifier: Programming Language :: Python :: 3
Classifier: Programming Language :: Python :: 3.7
Classifier: Programming Language :: Python :: 3.8
Classifier: Programming Language :: Python :: 3.9
Classifier: Programming Language :: Python :: 3.10
Classifier: Topic :: Scientific/Engineering :: Artificial Intelligence
Requires-Python: >=3.7
License-File: LICENSE
Requires-Dist: torch >=2.0.0
Requires-Dist: opencv-python
Requires-Dist: diffusers ==0.27.2
Requires-Dist: huggingface-hub ==0.25.2
Requires-Dist: accelerate
Requires-Dist: peft ==0.7.1
Requires-Dist: transformers >=4.39.1
Requires-Dist: safetensors
Requires-Dist: controlnet-aux ==0.0.3
Requires-Dist: fastapi ==0.108.0
Requires-Dist: uvicorn
Requires-Dist: python-multipart
Requires-Dist: python-socketio ==5.7.2
Requires-Dist: typer
Requires-Dist: pydantic >=2.5.2
Requires-Dist: rich
Requires-Dist: loguru
Requires-Dist: yacs
Requires-Dist: piexif ==1.1.3
Requires-Dist: omegaconf
Requires-Dist: easydict
Requires-Dist: gradio ==4.21.0
Requires-Dist: typer-config ==1.4.0
Requires-Dist: Pillow ==9.5.0
